op_secrets_backend/__init__.py
op_secrets_backend/op_secrets_backend.py
op_secrets_backend-0.1.8.dist-info/METADATA
op_secrets_backend-0.1.8.dist-info/WHEEL
op_secrets_backend-0.1.8.dist-info/licenses/LICENSE
op_secrets_backend-0.1.8.dist-info/RECORD
